corebmtk/__init__.py
corebmtk-0.1.1.dist-info/LICENSE
corebmtk-0.1.1.dist-info/METADATA
corebmtk-0.1.1.dist-info/WHEEL
corebmtk-0.1.1.dist-info/top_level.txt
corebmtk-0.1.1.dist-info/RECORD
